cpacman/__init__.py
cpacman/package.py
cpacman/packagemanager.py
cpacman/run.py
cpacman-1.0.4.dist-info/METADATA
cpacman-1.0.4.dist-info/WHEEL
cpacman-1.0.4.dist-info/entry_points.txt
cpacman-1.0.4.dist-info/top_level.txt
cpacman-1.0.4.dist-info/RECORD
