Metadata-Version: 2.1
Name: cpacman
Version: 1.0.4
Summary: UNKNOWN
Home-page: https://github.com/YoungMeatBoy/cpacman.git
Author: Miasnenko Dmitry
Author-email: cl0wzed.exe@gmail.com
License: UNKNOWN
Platform: UNKNOWN
Requires-Dist: requests
